{
  "best_metric": 0.6899436712265015,
  "best_model_checkpoint": "./results/run-0/checkpoint-500",
  "epoch": 3.194888178913738,
  "global_step": 500,
  "is_hyper_param_search": true,
  "is_local_process_zero": true,
  "is_world_process_zero": true,
  "log_history": [
    {
      "epoch": 3.19,
      "learning_rate": 5.961538461538461e-05,
      "loss": 0.6942,
      "step": 500
    },
    {
      "epoch": 3.19,
      "eval_accuracy": 0.5564,
      "eval_loss": 0.6899436712265015,
      "eval_runtime": 17.5684,
      "eval_samples_per_second": 284.603,
      "eval_steps_per_second": 35.575,
      "step": 500
    }
  ],
  "max_steps": 624,
  "num_train_epochs": 4,
  "total_flos": 20931591605760.0,
  "trial_name": null,
  "trial_params": {
    "learning_rate": 0.0003,
    "per_device_train_batch_size": 64
  }
}
